artifacts_mcp_server.py
artifacts_mcp_server-0.1.0.dist-info/METADATA
artifacts_mcp_server-0.1.0.dist-info/WHEEL
artifacts_mcp_server-0.1.0.dist-info/entry_points.txt
artifacts_mcp_server-0.1.0.dist-info/licenses/LICENSE
artifacts_mcp_server-0.1.0.dist-info/RECORD
