Metadata-Version: 2.4
Name: artifacts-mcp-server
Version: 0.1.0
Summary: Zero-config MCP Server for AI code artifacts with AgentSphere
Project-URL: Homepage, https://github.com/yourusername/artifacts-mcp-server
Project-URL: Repository, https://github.com/yourusername/artifacts-mcp-server
Project-URL: Documentation, https://github.com/yourusername/artifacts-mcp-server#readme
Project-URL: Issues, https://github.com/yourusername/artifacts-mcp-server/issues
Author-email: Artifacts MCP <noreply@example.com>
License-Expression: MIT
License-File: LICENSE
Keywords: agentsphere,ai,artifacts,claude,mcp
Classifier: Development Status :: 4 - Beta
Classifier: Intended Audience :: Developers
Classifier: License :: OSI Approved :: MIT License
Classifier: Programming Language :: Python :: 3
Classifier: Programming Language :: Python :: 3.9
Classifier: Programming Language :: Python :: 3.10
Classifier: Programming Language :: Python :: 3.11
Classifier: Programming Language :: Python :: 3.12
Classifier: Topic :: Scientific/Engineering :: Artificial Intelligence
Classifier: Topic :: Software Development
Requires-Python: >=3.9
Requires-Dist: agentsphere>=0.1.0
Requires-Dist: fastmcp>=2.0.0
Provides-Extra: dev
Requires-Dist: black>=22.0.0; extra == 'dev'
Requires-Dist: pytest>=7.0.0; extra == 'dev'
Requires-Dist: ruff>=0.1.0; extra == 'dev'
